hybridmethod/__init__.py
hybridmethod/version.txt
hybridmethod-1.0.1.dist-info/licenses/LICENSE.md
hybridmethod-1.0.1.dist-info/METADATA
hybridmethod-1.0.1.dist-info/WHEEL
hybridmethod-1.0.1.dist-info/top_level.txt
hybridmethod-1.0.1.dist-info/zip-safe
hybridmethod-1.0.1.dist-info/RECORD
