Metadata-Version: 2.4
Name: hybridmethod
Version: 1.0.1
Summary: A hybrid method decorator for Python allowing methods to be called on classes and their instances.
Author: Daniel Sissman
License: MIT License
Project-URL: documentation, https://github.com/bluebinary/hybridmethod/blob/main/README.md
Project-URL: changelog, https://github.com/bluebinary/hybridmethod/blob/main/CHANGELOG.md
Project-URL: repository, https://github.com/bluebinary/hybridmethod
Project-URL: issues, https://github.com/bluebinary/hybridmethod/issues
Project-URL: homepage, https://github.com/bluebinary/hybridmethod
Keywords: hybrid method,class method,instance method,decorator
Classifier: Programming Language :: Python :: 3
Classifier: Programming Language :: Python :: 3.10
Classifier: Programming Language :: Python :: 3.11
Classifier: Programming Language :: Python :: 3.12
Classifier: Programming Language :: Python :: 3.13
Requires-Python: >=3.10
License-File: LICENSE.md
Requires-Dist: classicist
Provides-Extra: development
Requires-Dist: black==24.10.*; extra == "development"
Requires-Dist: pytest==8.3.*; extra == "development"
Requires-Dist: pytest-codeblocks==0.17.0; extra == "development"
Provides-Extra: distribution
Requires-Dist: build; extra == "distribution"
Requires-Dist: twine; extra == "distribution"
Requires-Dist: wheel; extra == "distribution"
Dynamic: license-file
